Workbook

Sheet Net Zero Projects
A1: THE CORPORATE — NET ZERO ABATEMENT PROJECT REGISTER — 2025–2045
A2: Shadow Carbon Price: | B2: $100 / tCO2e | C2: SBTi Framework: | D2: 1.5°C Aligned | E2: Gross Carbon Debt: | F2: 4,588,079 tCO2e | G2: SBTi Removals Cap: | H2: 458,808 tCO2e | I2: 2030 SBTi Gate: | J2: 784,217 tCO2e (−50% MB) | K2: Max DAC Liability: | L2: $91.8M at $200/t
A3: # | B3: Project Name | C3: Scope(s) | D3: Wave | E3: Status | F3: Max Abatement (tCO2e) | G3: CAPEX ($M) | H3: MAC ($/tCO2e) | I3: OPEX Saving ($M/yr) | J3: Start Year | K3: Target Completion | L3: Primary Facilities | M3: Notes / Trigger
A4: WAVE 1 — 2025–2027 | 7 levers | All MAC ≤ $15/t | Approved for immediate funding | 230,000 tCO2e
A5: 1 | B5: Logistics Modal Shift — Air to Sea | C5: Scope 3 | D5: Wave 1 | E5: Approved | F5: 90000 | G5: 0 | H5: -30 | I5: 2.7 | J5: 2025 | K5: 2027 | L5: Shenzhen Systems, Chennai Circuitry | M5: Highest-priority W1 lever. Zero CAPEX. $2.7M annual freight cost saving. Cat 4 reduction.
A6: 2 | B6: LED Retrofit & Lighting Controls | C6: Scope 1 & 2 | D6: Wave 1 | E6: In Planning | F6: 15000 | G6: 0.45 | H6: -45 | I6: 0.68 | J6: 2025 | K6: 2026 | L6: All 5 facilities | M6: Rapid payback ~8 months. Immediate electricity reduction across all sites.
A7: 3 | B7: Compressed Air Leak Detection | C7: Scope 1 & 2 | D7: Wave 1 | E7: Not Started | F7: 12000 | G7: 0.15 | H7: -65 | I7: 0.78 | J7: 2025 | K7: 2026 | L7: Hanoi Hub, Shenzhen Systems, Chennai Circuitry | M7: Low CAPEX, high ROI. Priority at high-volume production sites.
A8: 4 | B8: HVAC Optimisation & AI Sensors | C8: Scope 1 & 2 | D8: Wave 1 | E8: In Planning | F8: 25000 | G8: 1.2 | H8: -25 | I8: 0.63 | J8: 2025 | K8: 2027 | L8: Guadalajara Gigafactory, Shenzhen Systems | M8: Critical for dry room environments at Guadalajara. AI sensor overlay on existing HVAC.
A9: 5 | B9: Smart Building Management System | C9: Scope 1 & 2 | D9: Wave 1 | E9: Approved | F9: 33000 | G9: 2.1 | H9: -15 | I9: 0.5 | J9: 2025 | K9: 2027 | L9: All 5 facilities | M9: Central BMS deployment. Integrates LED, HVAC, compressed air monitoring.
A10: 6 | B10: On-site Rooftop Solar PV | C10: Scope 2 | D10: Wave 1 | E10: Approved | F10: 45000 | G10: 5.4 | H10: 5 | I10: -0.3 | J10: 2025 | K10: 2027 | L10: Guadalajara Gigafactory (priority), Chennai Circuitry, Hanoi Hub | M10: Guadalajara: 18% solar IRR premium — earliest payback. Chennai: India RPO 25% RE mandate by 2030 — non-discretionary. Hanoi rooftop currently empty — deploy by 2026.
A11: 7 | B11: Electric Forklift Fleet Transition | C11: Scope 1 | D11: Wave 1 | E11: Not Started | F11: 10000 | G11: 1.2 | H11: 15 | I11: 0.12 | J11: 2026 | K11: 2027 | L11: Shenzhen Systems, Hanoi Hub | M11: Replaces diesel mobile combustion. Prerequisite: Hanoi battery storage deployment first.
A12: WAVE 2 — 2028–2032 | 5 levers | MAC $20–$85/t | Approved | 400,000 tCO2e
A13: 8 | B13: Off-site Virtual PPA — Wind / Solar | C13: Scope 2 | D13: Wave 2 | E13: In Planning | F13: 70000 | G13: 0 | H13: 20 | I13: -0.4 | J13: 2028 | K13: 2032 | L13: Shenzhen Systems (priority), Wrocław Precision | M13: Zero CAPEX. $20/t MAC. Shenzhen: highest grid EF (0.581). Wrocław: EU CBAM pressure raises effective shadow price to $180/t. Largest MB vs LB gap closure.
A14: 9 | B14: Supplier Energy Efficiency Program | C14: Scope 3 | D14: Wave 2 | E14: Not Started | F14: 75000 | G14: 0.5 | H14: 25 | I14: 0 | J14: 2028 | K14: 2032 | L14: All facilities — procurement-led | M14: Tier 1 supplier engagement programme. Cat 3 and Cat 1 partial reduction. VP Procurement ownership.
A15: 10 | B15: Bio-based Polymers for Packaging | C15: Scope 3 | D15: Wave 2 | E15: Not Started | F15: 80000 | G15: 0 | H15: 55 | I15: 0 | J15: 2028 | K15: 2032 | L15: Shenzhen Systems, Hanoi Hub | M15: Material specification change. Targets Cat 1 polymer inputs. Zero CAPEX — supplier contract renegotiation.
A16: 11 | B16: 90% Recycled Aluminium Sourcing | C16: Scope 3 | D16: Wave 2 | E16: In Planning | F16: 140000 | G16: 0 | H16: 80 | I16: 0 | J16: 2028 | K16: 2032 | L16: Wrocław Precision (primary), Shenzhen Systems | M16: Largest single abatement lever in portfolio (140,000 tCO2e). Cat 1 aluminium & metals. Wrocław EU CBAM: $80/t on embodied carbon — effective MAC $180/t raises urgency. VP Procurement lead.
A17: 12 | B17: Industrial Heat Pumps | C17: Scope 1 | D17: Wave 2 | E17: Not Started | F17: 35000 | G17: 6.5 | H17: 85 | I17: 0.35 | J17: 2028 | K17: 2032 | L17: Wrocław Precision, Guadalajara Gigafactory | M17: Replaces natural gas for process heat. Wrocław CNC stress-relief ovens primary target. Guadalajara dry rooms secondary.
A18: WAVE 3 — 2033–2040 | 1 lever | MAC = $100/t | WATCH — annual MAC review required | 55,000 tCO2e
A19: 13 | B19: Supplier Renewable Energy Mandate (SBTi) | C19: Scope 3 | D19: Wave 3 | E19: Watch | F19: 55000 | G19: 0 | H19: 100 | I19: 0 | J19: 2033 | K19: 2040 | L19: All facilities — Tier 1 & Tier 2 suppliers | M19: MAC exactly at $100/t shadow price threshold. Annual MAC review from 2028 required. Escalate to CSO if MAC > $110/t for 2 consecutive quarters. Cat 3 and Cat 1 supplier energy use.
A20: WAVE 4 — 2040–2045 | DAC removals | $200/t | LAST RESORT — Board approval required | ≤458,808 tCO2e
A21: 14 | B21: Permanent Carbon Removals — DAC | C21: Removals | D21: Wave 4 | E21: Not Started | F21: 458808 | G21: 0 | H21: 200 | I21: 0 | J21: 2041 | K21: 2045 | L21: Corporate-level — not facility-specific | M21: LAST RESORT only. SBTi cap: 458,808 tCO2e max (10% gross debt). Max liability $91.8M at $200/t. Board approval required before any DAC contract is executed. Activated only after all operational levers exhausted. Do not exceed cap — triggers mandatory portfolio review.
A23: PORTFOLIO SUMMARY — WAVES 1–3 OPERATIONAL ABATEMENT
B24: Wave 1 — Approved levers (7) | F24: =F5+F6+F7+F8+F9+F10+F11 -> 230000 | G24: =G5+G6+G7+G8+G9+G10+G11 -> 10.5 | I24: =I5+I6+I7+I8+I9+I10+I11 -> 5.11
B25: Wave 2 — Approved levers (5) | F25: =F13+F14+F15+F16+F17 -> 400000 | G25: =G13+G14+G15+G16+G17 -> 7 | I25: =I13+I14+I15+I16+I17 -> -0.05
B26: Wave 3 — WATCH lever (1) | F26: =F19 -> 55000 | G26: =G19 -> 0 | I26: =I19 -> 0
B27: TOTAL OPERATIONAL ABATEMENT (W1+W2+W3) | F27: =F5+F6+F7+F8+F9+F10+F11+F13+F14+F15+F16+F17+F19 -> 685000 | G27: =G5+G6+G7+G8+G9+G10+G11+G13+G14+G15+G16+G17+G19 -> 17.5 | I27: =I5+I6+I7+I8+I9+I10+I11+I13+I14+I15+I16+I17+I19 -> 5.06
A29: PORTFOLIO GAP ANALYSIS vs GROSS CARBON DEBT
B30: Gross Carbon Debt to 2045 (5% growth, 22yr) | F30: 4588079
B31: Total Operational Abatement — W1+W2+W3 | F31: 635000
B32: Maximum DAC Removals — Wave 4 (SBTi cap) | F32: 458808
B33: Remaining Gap after all levers + DAC | F33: 3494271
B34: Portfolio coverage of gross debt (%) | F34: 0.138
A36: Source: The_Corporate_Net_Zero_2045_Strategy_v2.docx — 16 May 2026 — Approved by CSO | Status field is the live element — update as projects progress | Blue = inputs | Black = formulas | MAC: negative = cost saving

Sheet Emission Factors
A1: EMISSION FACTORS — 2023 BASELINE
A2: Factor Name | B2: Value | C2: Unit | D2: Scope / Category | E2: Notes
A3: Natural Gas | B3: 0.002034 | C3: tCO2e / m³ | D3: S1 Stationary | E3: IPCC AR6 — incl. CH4 & N2O
A4: Diesel (stationary) | B4: 2.68 | C4: tCO2e / tonne | D4: S1 Stationary | E4: IEA 2023
A5: LPG | B5: 1.54 | C5: tCO2e / tonne | D5: S1 Stationary | E5: IPCC default
A6: Coal (thermal) | B6: 2.42 | C6: tCO2e / tonne | D6: S1 Stationary | E6: IPCC 2006 GL
A7: Diesel (mobile) | B7: 2.653 | C7: tCO2e / tonne | D7: S1 Mobile | E7: GHG Protocol
A8: Petrol (mobile) | B8: 2.31 | C8: tCO2e / tonne | D8: S1 Mobile | E8: GHG Protocol
A9: Grid — Vietnam | B9: 0.4936 | C9: tCO2e / MWh | D9: S2 Electricity | E9: IEA 2022 VN grid
A10: Grid — Mexico | B10: 0.454 | C10: tCO2e / MWh | D10: S2 Electricity | E10: SEMARNAT 2022
A11: Grid — China | B11: 0.581 | C11: tCO2e / MWh | D11: S2 Electricity | E11: CEA 2022
A12: Grid — Poland | B12: 0.726 | C12: tCO2e / MWh | D12: S2 Electricity | E12: KOBiZE 2022
A13: Grid — India | B13: 0.708 | C13: tCO2e / MWh | D13: S2 Electricity | E13: CEA India 2022
A14: Renewable (PPA/REC) | B14: 0 | C14: tCO2e / MWh | D14: S2 Market-based | E14: GHG Protocol MB method
A16: Note: All factors are mock/illustrative values for dashboard modelling. Replace with certified factors for compliance reporting.

Sheet Scope 1 — Detail
A1: SCOPE 1 EMISSIONS & ENERGY CONSUMPTION — 2023
B2: STATIONARY COMBUSTION | I2: MOBILE COMBUSTION
A3: Facility | B3: Nat. Gas (m³) | C3: Nat. Gas (tCO2e) | D3: Diesel Stat. (t) | E3: Diesel Stat. (tCO2e) | F3: LPG (t) | G3: LPG (tCO2e) | H3: Total Stationary (tCO2e) | I3: Diesel Mobile (t) | J3: Diesel Mobile (tCO2e) | K3: Petrol Mobile (t) | L3: Total Mobile (tCO2e)
A4: Hanoi Hub | B4: 2800000 | C4: =B4*'Emission Factors'!B3 -> 5695.2 | D4: 0 | E4: =D4*'Emission Factors'!B4 -> 0 | F4: 120 | G4: =F4*'Emission Factors'!B5 -> 184.8 | H4: =C4+E4+G4 -> 5880 | I4: 85 | J4: =I4*'Emission Factors'!B7 -> 225.505 | K4: 30 | L4: =J4+K4*'Emission Factors'!B8 -> 294.805
A5: Guadalajara Gigafactory | B5: 1400000 | C5: =B5*'Emission Factors'!B3 -> 2847.6 | D5: 0 | E5: =D5*'Emission Factors'!B4 -> 0 | F5: 60 | G5: =F5*'Emission Factors'!B5 -> 92.4 | H5: =C5+E5+G5 -> 2940 | I5: 55 | J5: =I5*'Emission Factors'!B7 -> 145.915 | K5: 20 | L5: =J5+K5*'Emission Factors'!B8 -> 192.115
A6: Shenzhen Systems | B6: 3500000 | C6: =B6*'Emission Factors'!B3 -> 7119 | D6: 0 | E6: =D6*'Emission Factors'!B4 -> 0 | F6: 80 | G6: =F6*'Emission Factors'!B5 -> 123.2 | H6: =C6+E6+G6 -> 7242.2 | I6: 190 | J6: =I6*'Emission Factors'!B7 -> 504.07 | K6: 95 | L6: =J6+K6*'Emission Factors'!B8 -> 723.52
A7: Wrocław Precision | B7: 1900000 | C7: =B7*'Emission Factors'!B3 -> 3864.6 | D7: 0 | E7: =D7*'Emission Factors'!B4 -> 0 | F7: 220 | G7: =F7*'Emission Factors'!B5 -> 338.8 | H7: =C7+E7+G7 -> 4203.4 | I7: 40 | J7: =I7*'Emission Factors'!B7 -> 106.12 | K7: 15 | L7: =J7+K7*'Emission Factors'!B8 -> 140.77
A8: Chennai Circuitry | B8: 1200000 | C8: =B8*'Emission Factors'!B3 -> 2440.8 | D8: 680 | E8: =D8*'Emission Factors'!B4 -> 1822.4 | F8: 40 | G8: =F8*'Emission Factors'!B5 -> 61.6 | H8: =C8+E8+G8 -> 4324.8 | I8: 75 | J8: =I8*'Emission Factors'!B7 -> 198.975 | K8: 25 | L8: =J8+K8*'Emission Factors'!B8 -> 256.725
A9: TOTAL | B9: =SUM(B4:B8) -> 10800000 | C9: =SUM(C4:C8) -> 21967.2 | D9: =SUM(D4:D8) -> 680 | E9: =SUM(E4:E8) -> 1822.4 | F9: =SUM(F4:F8) -> 520 | G9: =SUM(G4:G8) -> 800.8 | H9: =SUM(H4:H8) -> 24590.4 | I9: =SUM(I4:I8) -> 445 | ... L9: =SUM(L4:L8) -> 1607.935

Sheet Scope 2 — Detail
A1: SCOPE 2 EMISSIONS & ENERGY CONSUMPTION — 2023
B2: ELECTRICITY CONSUMPTION | G2: LOCATION-BASED | I2: MARKET-BASED
A3: Facility | B3: Total Elec. (MWh) | C3: Grid Elec. (MWh) | D3: Renewables PPA (MWh) | E3: % Renewable | F3: Gas EF Applied | G3: LB Emissions (tCO2e) | H3: LB Intensity (tCO2e/MWh) | I3: MB Emissions (tCO2e) | J3: MB Intensity (tCO2e/MWh)
A4: Hanoi Hub | B4: 58000 | C4: =B4-D4 -> 50000 | D4: 8000 | E4: =IFERROR(D4/B4,0) -> 0.13793103 | F4: EF:B9 | G4: =B4*'Emission Factors'!B9 -> 28628.8 | H4: =IFERROR(G4/B4,0) -> 0.4936 | I4: =C4*'Emission Factors'!B9+D4*'Emission Factors'!B14 -> 24680 | J4: =IFERROR(I4/B4,0) -> 0.42551724
A5: Guadalajara Gigafactory | B5: 72000 | C5: =B5-D5 -> 50000 | D5: 22000 | E5: =IFERROR(D5/B5,0) -> 0.30555556 | F5: EF:B10 | G5: =B5*'Emission Factors'!B10 -> 32688 | H5: =IFERROR(G5/B5,0) -> 0.454 | I5: =C5*'Emission Factors'!B10+D5*'Emission Factors'!B14 -> 22700 | J5: =IFERROR(I5/B5,0) -> 0.31527778
A6: Shenzhen Systems | B6: 94000 | C6: =B6-D6 -> 88000 | D6: 6000 | E6: =IFERROR(D6/B6,0) -> 0.063829787 | F6: EF:B11 | G6: =B6*'Emission Factors'!B11 -> 54614 | H6: =IFERROR(G6/B6,0) -> 0.581 | I6: =C6*'Emission Factors'!B11+D6*'Emission Factors'!B14 -> 51128 | J6: =IFERROR(I6/B6,0) -> 0.54391489
A7: Wrocław Precision | B7: 31000 | C7: =B7-D7 -> 22000 | D7: 9000 | E7: =IFERROR(D7/B7,0) -> 0.29032258 | F7: EF:B12 | G7: =B7*'Emission Factors'!B12 -> 22506 | H7: =IFERROR(G7/B7,0) -> 0.726 | I7: =C7*'Emission Factors'!B12+D7*'Emission Factors'!B14 -> 15972 | J7: =IFERROR(I7/B7,0) -> 0.51522581
A8: Chennai Circuitry | B8: 41000 | C8: =B8-D8 -> 37000 | D8: 4000 | E8: =IFERROR(D8/B8,0) -> 0.097560976 | F8: EF:B13 | G8: =B8*'Emission Factors'!B13 -> 29028 | H8: =IFERROR(G8/B8,0) -> 0.708 | I8: =C8*'Emission Factors'!B13+D8*'Emission Factors'!B14 -> 26196 | J8: =IFERROR(I8/B8,0) -> 0.63892683
A9: TOTAL | B9: =SUM(B4:B8) -> 296000 | C9: =SUM(C4:C8) -> 247000 | D9: =SUM(D4:D8) -> 49000 | E9: =IFERROR(D9/B9,0) -> 0.16554054 | G9: =SUM(G4:G8) -> 167464.8 | H9: =IFERROR(SUM(H4:H8)/COUNT(H4:H8),0) -> 0.59252 | I9: =SUM(I4:I8) -> 140676 | J9: =IFERROR(SUM(J4:J8)/COUNT(J4:J8),0) -> 0.48777251

Sheet Scope 3 — Detail
A1: SCOPE 3 EMISSIONS — CATEGORY BREAKDOWN — 2023
A2: Category | B2: Hanoi Hub | C2: Guadalajara Gigafactory | D2: Shenzhen Systems | E2: Wrocław Precision | F2: Chennai Circuitry | G2: TOTAL
A3: ── UPSTREAM ──
A4: Cat 1: Purchased Goods & Services | B4: 128400 | C4: 89200 | D4: 312000 | E4: 42100 | F4: 156800 | G4: =SUM(B4:F4) -> 728500
A5: Cat 2: Capital Goods | B5: 8200 | C5: 11400 | D5: 14600 | E5: 9800 | F5: 7200 | G5: =SUM(B5:F5) -> 51200
A6: Cat 3: Fuel & Energy-Related | B6: 4100 | C6: 5800 | D6: 9200 | E6: 3600 | F6: 4900 | G6: =SUM(B6:F6) -> 27600
A7: Cat 4: Upstream Transportation | B7: 22100 | C7: 18600 | D7: 48200 | E7: 12400 | F7: 31600 | G7: =SUM(B7:F7) -> 132900
A8: Cat 5: Waste Generated in Ops | B8: 1200 | C8: 980 | D8: 2400 | E8: 640 | F8: 1800 | G8: =SUM(B8:F8) -> 7020
A9: Cat 6: Business Travel | B9: 420 | C9: 380 | D9: 880 | E9: 310 | F9: 540 | G9: =SUM(B9:F9) -> 2530
A10: Cat 7: Employee Commuting | B10: 3200 | C10: 2600 | D10: 8400 | E10: 1800 | F10: 4200 | G10: =SUM(B10:F10) -> 20200
A11: Cat 8: Upstream Leased Assets | B11: 600 | C11: 400 | D11: 900 | E11: 200 | F11: 700 | G11: =SUM(B11:F11) -> 2800
A12: ── DOWNSTREAM ──
A13: Cat 9: Downstream Transport | B13: 9800 | C13: 7200 | D13: 24600 | E13: 4100 | F13: 14200 | G13: =SUM(B13:F13) -> 59900
A14: Cat 10: Processing of Sold Prods | B14: 0 | C14: 0 | D14: 0 | E14: 0 | F14: 0 | G14: =SUM(B14:F14) -> 0
A15: Cat 11: Use of Sold Products | B15: 42000 | C15: 68000 | D15: 110000 | E15: 12000 | F15: 88000 | G15: =SUM(B15:F15) -> 320000
A16: Cat 12: End-of-Life Treatment | B16: 6400 | C16: 8200 | D16: 18400 | E16: 2200 | F16: 12600 | G16: =SUM(B16:F16) -> 47800
A17: Cat 13: Downstream Leased Assets | B17: 200 | C17: 150 | D17: 400 | E17: 80 | F17: 280 | G17: =SUM(B17:F17) -> 1110
A18: Cat 14: Franchises | B18: 0 | C18: 0 | D18: 0 | E18: 0 | F18: 0 | G18: =SUM(B18:F18) -> 0
A19: Cat 15: Investments | B19: 0 | C19: 0 | D19: 0 | E19: 0 | F19: 0 | G19: =SUM(B19:F19) -> 0
A20: TOTAL SCOPE 3 (tCO2e) | B20: =B4+B5+B6+B7+B8+B9+B10+B11+B13+B14+B15+B16+B17+B18+B19 -> 226620 | C20: =C4+C5+C6+C7+C8+C9+C10+C11+C13+C14+C15+C16+C17+C18+C19 -> 212910 | D20: =D4+D5+D6+D7+D8+D9+D10+D11+D13+D14+D15+D16+D17+D18+D19 -> 549980 | E20: =E4+E5+E6+E7+E8+E9+E10+E11+E13+E14+E15+E16+E17+E18+E19 -> 89230 | F20: =F4+F5+F6+F7+F8+F9+F10+F11+F13+F14+F15+F16+F17+F18+F19 -> 322820 | G20: =G4+G5+G6+G7+G8+G9+G10+G11+G13+G14+G15+G16+G17+G18+G19 -> 1401560

Sheet Energy Mix
A1: ENERGY MIX & CONSUMPTION DETAIL — 2023
A2: Facility | B2: Nat. Gas (MWh eq.) | C2: Diesel Stat. (MWh eq.) | D2: LPG (MWh eq.) | E2: Total Fossil Thermal (MWh eq.) | F2: Grid Electricity (MWh) | G2: Renewable Electricity (MWh) | H2: Total Electricity (MWh) | I2: Total Energy (MWh eq.)
A3: Hanoi Hub | B3: ='Scope 1 — Detail'!B4*0.01055 -> 29540 | C3: ='Scope 1 — Detail'!D4*11.63 -> 0 | D3: ='Scope 1 — Detail'!F4*13.1 -> 1572 | E3: =B3+C3+D3 -> 31112 | F3: ='Scope 2 — Detail'!C4 -> 50000 | G3: ='Scope 2 — Detail'!D4 -> 8000 | H3: =F3+G3 -> 58000 | I3: =E3+H3 -> 89112
A4: Guadalajara Gigafactory | B4: ='Scope 1 — Detail'!B5*0.01055 -> 14770 | C4: ='Scope 1 — Detail'!D5*11.63 -> 0 | D4: ='Scope 1 — Detail'!F5*13.1 -> 786 | E4: =B4+C4+D4 -> 15556 | F4: ='Scope 2 — Detail'!C5 -> 50000 | G4: ='Scope 2 — Detail'!D5 -> 22000 | H4: =F4+G4 -> 72000 | I4: =E4+H4 -> 87556
A5: Shenzhen Systems | B5: ='Scope 1 — Detail'!B6*0.01055 -> 36925 | C5: ='Scope 1 — Detail'!D6*11.63 -> 0 | D5: ='Scope 1 — Detail'!F6*13.1 -> 1048 | E5: =B5+C5+D5 -> 37973 | F5: ='Scope 2 — Detail'!C6 -> 88000 | G5: ='Scope 2 — Detail'!D6 -> 6000 | H5: =F5+G5 -> 94000 | I5: =E5+H5 -> 131973
A6: Wrocław Precision | B6: ='Scope 1 — Detail'!B7*0.01055 -> 20045 | C6: ='Scope 1 — Detail'!D7*11.63 -> 0 | D6: ='Scope 1 — Detail'!F7*13.1 -> 2882 | E6: =B6+C6+D6 -> 22927 | F6: ='Scope 2 — Detail'!C7 -> 22000 | G6: ='Scope 2 — Detail'!D7 -> 9000 | H6: =F6+G6 -> 31000 | I6: =E6+H6 -> 53927
A7: Chennai Circuitry | B7: ='Scope 1 — Detail'!B8*0.01055 -> 12660 | C7: ='Scope 1 — Detail'!D8*11.63 -> 7908.4 | D7: ='Scope 1 — Detail'!F8*13.1 -> 524 | E7: =B7+C7+D7 -> 21092.4 | F7: ='Scope 2 — Detail'!C8 -> 37000 | G7: ='Scope 2 — Detail'!D8 -> 4000 | H7: =F7+G7 -> 41000 | I7: =E7+H7 -> 62092.4
A8: TOTAL | B8: =SUM(B3:B7) -> 113940 | C8: =SUM(C3:C7) -> 7908.4 | D8: =SUM(D3:D7) -> 6812 | E8: =SUM(E3:E7) -> 128660.4 | F8: =SUM(F3:F7) -> 247000 | G8: =SUM(G3:G7) -> 49000 | H8: =SUM(H3:H7) -> 296000 | I8: =SUM(I3:I7) -> 424660.4

Sheet Master Summary
A1: THE CORPORATE — EMISSIONS & ENERGY MASTER SUMMARY — 2023
A2: Facility | B2: S1 Stationary (tCO2e) | C2: S1 Mobile (tCO2e) | D2: Total Scope 1 (tCO2e) | E2: S2 LB (tCO2e) | F2: S2 MB (tCO2e) | G2: S1+S2 LB (tCO2e) | H2: Scope 3 (tCO2e) | I2: Total GHG LB (tCO2e) | J2: Total Electricity (MWh) | K2: % Renewable
A3: Hanoi Hub (Vietnam) | B3: ='Scope 1 — Detail'!H4 -> 5880 | C3: ='Scope 1 — Detail'!L4 -> 294.805 | D3: =B3+C3 -> 6174.805 | E3: ='Scope 2 — Detail'!G4 -> 28628.8 | F3: ='Scope 2 — Detail'!I4 -> 24680 | G3: =D3+E3 -> 34803.605 | H3: ='Scope 3 — Detail'!B4+'Scope 3 — Detail'!B5+'Scope 3 — Detail'!B6+'Scope 3 — Detail'!B7+'Scope 3 — Detail'!B8+'Scope 3 — Detail'!B9+'Scope 3 — Detail'!B10+'Scope 3 — Detail'!B11+'Scope 3 — Detail'!B13+'Scope 3 — Detail'!B14+'Scope 3 — Detail'!B15+'Scope 3 — Detail'!B16+'Scope 3 — Detail'!B17+'Scope 3 — Detail'!B18+'Scope 3 — Detail'!B19 -> 226620 | I3: =G3+H3 -> 261423.61 | J3: ='Scope 2 — Detail'!B4 -> 58000 | K3: ='Scope 2 — Detail'!E4 -> 0.13793103
A4: Guadalajara Gigafactory (Mexico) | B4: ='Scope 1 — Detail'!H5 -> 2940 | C4: ='Scope 1 — Detail'!L5 -> 192.115 | D4: =B4+C4 -> 3132.115 | E4: ='Scope 2 — Detail'!G5 -> 32688 | F4: ='Scope 2 — Detail'!I5 -> 22700 | G4: =D4+E4 -> 35820.115 | H4: ='Scope 3 — Detail'!C4+'Scope 3 — Detail'!C5+'Scope 3 — Detail'!C6+'Scope 3 — Detail'!C7+'Scope 3 — Detail'!C8+'Scope 3 — Detail'!C9+'Scope 3 — Detail'!C10+'Scope 3 — Detail'!C11+'Scope 3 — Detail'!C13+'Scope 3 — Detail'!C14+'Scope 3 — Detail'!C15+'Scope 3 — Detail'!C16+'Scope 3 — Detail'!C17+'Scope 3 — Detail'!C18+'Scope 3 — Detail'!C19 -> 212910 | I4: =G4+H4 -> 248730.11 | J4: ='Scope 2 — Detail'!B5 -> 72000 | K4: ='Scope 2 — Detail'!E5 -> 0.30555556
A5: Shenzhen Systems (China) | B5: ='Scope 1 — Detail'!H6 -> 7242.2 | C5: ='Scope 1 — Detail'!L6 -> 723.52 | D5: =B5+C5 -> 7965.72 | E5: ='Scope 2 — Detail'!G6 -> 54614 | F5: ='Scope 2 — Detail'!I6 -> 51128 | G5: =D5+E5 -> 62579.72 | H5: ='Scope 3 — Detail'!D4+'Scope 3 — Detail'!D5+'Scope 3 — Detail'!D6+'Scope 3 — Detail'!D7+'Scope 3 — Detail'!D8+'Scope 3 — Detail'!D9+'Scope 3 — Detail'!D10+'Scope 3 — Detail'!D11+'Scope 3 — Detail'!D13+'Scope 3 — Detail'!D14+'Scope 3 — Detail'!D15+'Scope 3 — Detail'!D16+'Scope 3 — Detail'!D17+'Scope 3 — Detail'!D18+'Scope 3 — Detail'!D19 -> 549980 | I5: =G5+H5 -> 612559.72 | J5: ='Scope 2 — Detail'!B6 -> 94000 | K5: ='Scope 2 — Detail'!E6 -> 0.063829787
A6: Wrocław Precision (Poland) | B6: ='Scope 1 — Detail'!H7 -> 4203.4 | C6: ='Scope 1 — Detail'!L7 -> 140.77 | D6: =B6+C6 -> 4344.17 | E6: ='Scope 2 — Detail'!G7 -> 22506 | F6: ='Scope 2 — Detail'!I7 -> 15972 | G6: =D6+E6 -> 26850.17 | H6: ='Scope 3 — Detail'!E4+'Scope 3 — Detail'!E5+'Scope 3 — Detail'!E6+'Scope 3 — Detail'!E7+'Scope 3 — Detail'!E8+'Scope 3 — Detail'!E9+'Scope 3 — Detail'!E10+'Scope 3 — Detail'!E11+'Scope 3 — Detail'!E13+'Scope 3 — Detail'!E14+'Scope 3 — Detail'!E15+'Scope 3 — Detail'!E16+'Scope 3 — Detail'!E17+'Scope 3 — Detail'!E18+'Scope 3 — Detail'!E19 -> 89230 | I6: =G6+H6 -> 116080.17 | J6: ='Scope 2 — Detail'!B7 -> 31000 | K6: ='Scope 2 — Detail'!E7 -> 0.29032258
A7: Chennai Circuitry (India) | B7: ='Scope 1 — Detail'!H8 -> 4324.8 | C7: ='Scope 1 — Detail'!L8 -> 256.725 | D7: =B7+C7 -> 4581.525 | E7: ='Scope 2 — Detail'!G8 -> 29028 | F7: ='Scope 2 — Detail'!I8 -> 26196 | G7: =D7+E7 -> 33609.525 | H7: ='Scope 3 — Detail'!F4+'Scope 3 — Detail'!F5+'Scope 3 — Detail'!F6+'Scope 3 — Detail'!F7+'Scope 3 — Detail'!F8+'Scope 3 — Detail'!F9+'Scope 3 — Detail'!F10+'Scope 3 — Detail'!F11+'Scope 3 — Detail'!F13+'Scope 3 — Detail'!F14+'Scope 3 — Detail'!F15+'Scope 3 — Detail'!F16+'Scope 3 — Detail'!F17+'Scope 3 — Detail'!F18+'Scope 3 — Detail'!F19 -> 322820 | I7: =G7+H7 -> 356429.53 | J7: ='Scope 2 — Detail'!B8 -> 41000 | K7: ='Scope 2 — Detail'!E8 -> 0.097560976
A8: COMPANY TOTAL | B8: =SUM(B3:B7) -> 24590.4 | C8: =SUM(C3:C7) -> 1607.935 | D8: =SUM(D3:D7) -> 26198.335 | E8: =SUM(E3:E7) -> 167464.8 | F8: =SUM(F3:F7) -> 140676 | G8: =SUM(G3:G7) -> 193663.14 | H8: =SUM(H3:H7) -> 1401560 | I8: =SUM(I3:I7) -> 1595223.1 | J8: =SUM(J3:J7) -> 296000 | K8: =IFERROR(SUM('Scope 2 — Detail'!D4:D8)/SUM('Scope 2 — Detail'!B4:B8),0) -> 0.16554054
A11: KEY PERFORMANCE INDICATORS
A12: Total Scope 1+2 (LB) tCO2e | D12: =G8 -> 193663.14
A13: Total Scope 3 tCO2e | D13: =H8 -> 1401560
A14: Total GHG (all scopes) tCO2e | D14: =I8 -> 1595223.1
A15: Total Electricity MWh | D15: =J8 -> 296000
A16: Corporate Renewable % | D16: =K8 -> 0.16554054

Sheet Data Dictionary
A1: DATA DICTIONARY — THE CORPORATE EMISSIONS MODEL
A2: Field / Column | B2: Description | C2: Unit | D2: Sheet | E2: Notes
A3: Nat. Gas Consumed | B3: Volume of natural gas consumed in stationary combustion | C3: m³ | D3: S1 Detail | E3: Boilers, furnaces, dryers
A4: Nat. Gas Emissions | B4: CO2e from natural gas × emission factor | C4: tCO2e | D4: S1 Detail | E4: EF: 0.002034 tCO2e/m³
A5: Diesel (Stationary) | B5: Diesel fuel for backup generators and stationary engines | C5: tonnes | D5: S1 Detail | E5: Key for Chennai (grid instability)
A6: Diesel (Mobile) | B6: Diesel for forklifts, on-site vehicles | C6: tonnes | D6: S1 Detail | E6: EF: 2.653 tCO2e/t
A7: Petrol (Mobile) | B7: Petrol/gasoline for on-site light vehicles | C7: tonnes | D7: S1 Detail | E7: EF: 2.31 tCO2e/t
A8: Total Stationary S1 | B8: Sum of all stationary combustion emissions | C8: tCO2e | D8: S1 Detail | E8: Formula: nat gas + diesel + LPG
A9: Total Mobile S1 | B9: Sum of all mobile combustion emissions | C9: tCO2e | D9: S1 Detail | E9: Formula: diesel mob + petrol mob
A10: Total Electricity | B10: Total electricity consumed (grid + renewables) | C10: MWh | D10: S2 Detail | E10: Includes PPA/REC volumes
A11: Grid Electricity | B11: Electricity from national grid (location-based) | C11: MWh | D11: S2 Detail | E11: Grid elec = Total minus Renewables PPA
A12: Renewables PPA | B12: Electricity covered by PPAs or RECs | C12: MWh | D12: S2 Detail | E12: Zero-carbon under market-based
A13: LB Emissions | B13: Location-based S2: all elec × country grid EF | C13: tCO2e | D13: S2 Detail | E13: GHG Protocol location method
... A20: LPG (MWh eq.) | B20: LPG converted to MWh equivalent | C20: MWh | D20: Energy Mix | E20: Factor: 13.10 MWh/tonne
